inovyo_api/__init__.py
inovyo_api/auth.py
inovyo_api-0.1.1.dist-info/METADATA
inovyo_api-0.1.1.dist-info/WHEEL
inovyo_api-0.1.1.dist-info/top_level.txt
inovyo_api-0.1.1.dist-info/RECORD
