Metadata-Version: 2.1
Name: inovyo_api
Version: 0.1.1
Summary: Biblioteca para integração com as APIs da Inovyo
Home-page: 
Author: Modulo-Inovyo-API
Author-email: admin@inovyo.com
Requires-Dist: requests
